Workbook

Sheet How to Use
B2: VEYN — BUSINESS HUB TEMPLATE
B3: Billing & Insurer Tracker
B5: Log every self-pay and insurer invoice in one place, see what's outstanding at a glance, and total up billing activity without needing your PMS's own reporting.
B6: Fill in the blue cells on the Billing Log tab as invoices go out and payments come in. Everything else calculates itself — outstanding balance, days outstanding and status all update automatically.
B8: HOW TO READ THIS WORKBOOK
B9: Colour | C9: Meaning
B10: Blue text | C10: Type into this cell — it won't overwrite a formula
B11: Black text | C11: Calculated automatically — leave alone
B12: Gold row | C12: Unpaid or partially paid
B13: Green row | C13: Paid in full
B15: This template is general guidance, not financial, tax or legal advice — check figures relevant to your own situation.
B17: Privacy note: use patient initials or an internal reference number in these trackers, never full identifying details, in line with GDPR good practice.

Sheet Billing Log
A1: Billing Log
A2: One row per invoice · totals on the Summary tab
A4: Date Invoiced | B4: Patient Ref | C4: Consultant | D4: Procedure / CCSD Code | E4: Payer Type | F4: Insurer | G4: Invoice Amount (£) | H4: Amount Received (£) | I4: Outstanding (£) | J4: Status | K4: Date Paid / Remitted | L4: Days Outstanding | M4: Notes
I5: =IF(G5="","",G5-H5) | J5: =IF(G5="","",IF(H5=0,"Unpaid",IF(H5<G5,"Partial","Paid"))) | L5: =IF(OR(G5="",J5="Paid"),"",TODAY()-A5)
I6: =IF(G6="","",G6-H6) | J6: =IF(G6="","",IF(H6=0,"Unpaid",IF(H6<G6,"Partial","Paid"))) | L6: =IF(OR(G6="",J6="Paid"),"",TODAY()-A6)
I7: =IF(G7="","",G7-H7) | J7: =IF(G7="","",IF(H7=0,"Unpaid",IF(H7<G7,"Partial","Paid"))) | L7: =IF(OR(G7="",J7="Paid"),"",TODAY()-A7)
I8: =IF(G8="","",G8-H8) | J8: =IF(G8="","",IF(H8=0,"Unpaid",IF(H8<G8,"Partial","Paid"))) | L8: =IF(OR(G8="",J8="Paid"),"",TODAY()-A8)
I9: =IF(G9="","",G9-H9) | J9: =IF(G9="","",IF(H9=0,"Unpaid",IF(H9<G9,"Partial","Paid"))) | L9: =IF(OR(G9="",J9="Paid"),"",TODAY()-A9)
I10: =IF(G10="","",G10-H10) | J10: =IF(G10="","",IF(H10=0,"Unpaid",IF(H10<G10,"Partial","Paid"))) | L10: =IF(OR(G10="",J10="Paid"),"",TODAY()-A10)
I11: =IF(G11="","",G11-H11) | J11: =IF(G11="","",IF(H11=0,"Unpaid",IF(H11<G11,"Partial","Paid"))) | L11: =IF(OR(G11="",J11="Paid"),"",TODAY()-A11)
I12: =IF(G12="","",G12-H12) | J12: =IF(G12="","",IF(H12=0,"Unpaid",IF(H12<G12,"Partial","Paid"))) | L12: =IF(OR(G12="",J12="Paid"),"",TODAY()-A12)
I13: =IF(G13="","",G13-H13) | J13: =IF(G13="","",IF(H13=0,"Unpaid",IF(H13<G13,"Partial","Paid"))) | L13: =IF(OR(G13="",J13="Paid"),"",TODAY()-A13)
I14: =IF(G14="","",G14-H14) | J14: =IF(G14="","",IF(H14=0,"Unpaid",IF(H14<G14,"Partial","Paid"))) | L14: =IF(OR(G14="",J14="Paid"),"",TODAY()-A14)
I15: =IF(G15="","",G15-H15) | J15: =IF(G15="","",IF(H15=0,"Unpaid",IF(H15<G15,"Partial","Paid"))) | L15: =IF(OR(G15="",J15="Paid"),"",TODAY()-A15)
I16: =IF(G16="","",G16-H16) | J16: =IF(G16="","",IF(H16=0,"Unpaid",IF(H16<G16,"Partial","Paid"))) | L16: =IF(OR(G16="",J16="Paid"),"",TODAY()-A16)
... I64: =IF(G64="","",G64-H64) | J64: =IF(G64="","",IF(H64=0,"Unpaid",IF(H64<G64,"Partial","Paid"))) | L64: =IF(OR(G64="",J64="Paid"),"",TODAY()-A64)

Sheet Summary
A1: Billing Summary
A2: Updates automatically from the Billing Log tab
A4: Totals
A5: Total Invoiced | B5: =SUM('Billing Log'!G5:G64) -> 0
A6: Total Received | B6: =SUM('Billing Log'!H5:H64) -> 0
A7: Total Outstanding | B7: =SUM('Billing Log'!I5:I64) -> 0
A8: Invoices Logged | B8: =COUNTA('Billing Log'!A5:A64) -> 0
A9: Unpaid Count | B9: =COUNTIF('Billing Log'!J5:J64,"Unpaid") -> 0
A10: Partial Count | B10: =COUNTIF('Billing Log'!J5:J64,"Partial") -> 0
A11: Paid Count | B11: =COUNTIF('Billing Log'!J5:J64,"Paid") -> 0
A13: By Insurer
A14: Insurer | B14: Total Invoiced (£) | C14: Total Received (£) | D14: Outstanding (£)
A15: Self-Pay | B15: =SUMIF('Billing Log'!$E$5:$E$64,"Self-Pay",'Billing Log'!$G$5:$G$64) -> 0 | C15: =SUMIF('Billing Log'!$E$5:$E$64,"Self-Pay",'Billing Log'!$H$5:$H$64) -> 0 | D15: =SUMIF('Billing Log'!$E$5:$E$64,"Self-Pay",'Billing Log'!$I$5:$I$64) -> 0
A16: Bupa | B16: =SUMIF('Billing Log'!$F$5:$F$64,"Bupa",'Billing Log'!$G$5:$G$64) -> 0 | C16: =SUMIF('Billing Log'!$F$5:$F$64,"Bupa",'Billing Log'!$H$5:$H$64) -> 0 | D16: =SUMIF('Billing Log'!$F$5:$F$64,"Bupa",'Billing Log'!$I$5:$I$64) -> 0
A17: AXA Health | B17: =SUMIF('Billing Log'!$F$5:$F$64,"AXA Health",'Billing Log'!$G$5:$G$64) -> 0 | C17: =SUMIF('Billing Log'!$F$5:$F$64,"AXA Health",'Billing Log'!$H$5:$H$64) -> 0 | D17: =SUMIF('Billing Log'!$F$5:$F$64,"AXA Health",'Billing Log'!$I$5:$I$64) -> 0
A18: Vitality | B18: =SUMIF('Billing Log'!$F$5:$F$64,"Vitality",'Billing Log'!$G$5:$G$64) -> 0 | C18: =SUMIF('Billing Log'!$F$5:$F$64,"Vitality",'Billing Log'!$H$5:$H$64) -> 0 | D18: =SUMIF('Billing Log'!$F$5:$F$64,"Vitality",'Billing Log'!$I$5:$I$64) -> 0
A19: Aviva | B19: =SUMIF('Billing Log'!$F$5:$F$64,"Aviva",'Billing Log'!$G$5:$G$64) -> 0 | C19: =SUMIF('Billing Log'!$F$5:$F$64,"Aviva",'Billing Log'!$H$5:$H$64) -> 0 | D19: =SUMIF('Billing Log'!$F$5:$F$64,"Aviva",'Billing Log'!$I$5:$I$64) -> 0
A20: WPA | B20: =SUMIF('Billing Log'!$F$5:$F$64,"WPA",'Billing Log'!$G$5:$G$64) -> 0 | C20: =SUMIF('Billing Log'!$F$5:$F$64,"WPA",'Billing Log'!$H$5:$H$64) -> 0 | D20: =SUMIF('Billing Log'!$F$5:$F$64,"WPA",'Billing Log'!$I$5:$I$64) -> 0
A21: Healix | B21: =SUMIF('Billing Log'!$F$5:$F$64,"Healix",'Billing Log'!$G$5:$G$64) -> 0 | C21: =SUMIF('Billing Log'!$F$5:$F$64,"Healix",'Billing Log'!$H$5:$H$64) -> 0 | D21: =SUMIF('Billing Log'!$F$5:$F$64,"Healix",'Billing Log'!$I$5:$I$64) -> 0
A22: Other | B22: =SUMIF('Billing Log'!$F$5:$F$64,"Other",'Billing Log'!$G$5:$G$64) -> 0 | C22: =SUMIF('Billing Log'!$F$5:$F$64,"Other",'Billing Log'!$H$5:$H$64) -> 0 | D22: =SUMIF('Billing Log'!$F$5:$F$64,"Other",'Billing Log'!$I$5:$I$64) -> 0
