Workbook

Sheet How to Use
B2: VEYN — BUSINESS HUB TEMPLATE
B3: Income & Expense Log
B5: Tracks money in (client/consultant income) and money out (mileage and business expenses) in one place, with a running net-income summary — useful for self-assessment records if you're self-employed.
B6: This is general guidance only, not financial, tax or legal advice for your specific situation — check figures with an accountant before relying on them, in line with Veyn's Business Hub terms.
B8: HOW TO READ THIS WORKBOOK
B9: Colour | C9: Meaning
B10: Blue text | C10: Type into this cell — it won't overwrite a formula
B11: Black text | C11: Calculated automatically — leave alone
B12: Gold row | C12: Outstanding — not yet received
B13: Green row | C13: Received / paid
B15: This template is general guidance, not financial, tax or legal advice — check figures relevant to your own situation.
B17: Privacy note: use patient initials or an internal reference number in these trackers, never full identifying details, in line with GDPR good practice.

Sheet Income Log
A1: Income Log
A2: One row per payment — invoiced or received
A4: Date | B4: Consultant / Client | C4: Description | D4: Income Type | E4: Amount (£) | F4: Payment Status | G4: Notes

Sheet Expense & Mileage Log
A1: Expense & Mileage Log
A2: One row per expense or mileage claim
A4: Date | B4: Description | C4: Category | D4: Miles | E4: Mileage Rate (£/mile) | F4: Mileage Amount (£) | G4: Other Expense (£) | H4: Total (£) | I4: Notes
F5: =IF(OR(D5="",E5=""),"",D5*E5) | H5: =SUM(F5,G5) -> 0
F6: =IF(OR(D6="",E6=""),"",D6*E6) | H6: =SUM(F6,G6) -> 0
F7: =IF(OR(D7="",E7=""),"",D7*E7) | H7: =SUM(F7,G7) -> 0
F8: =IF(OR(D8="",E8=""),"",D8*E8) | H8: =SUM(F8,G8) -> 0
F9: =IF(OR(D9="",E9=""),"",D9*E9) | H9: =SUM(F9,G9) -> 0
F10: =IF(OR(D10="",E10=""),"",D10*E10) | H10: =SUM(F10,G10) -> 0
F11: =IF(OR(D11="",E11=""),"",D11*E11) | H11: =SUM(F11,G11) -> 0
F12: =IF(OR(D12="",E12=""),"",D12*E12) | H12: =SUM(F12,G12) -> 0
F13: =IF(OR(D13="",E13=""),"",D13*E13) | H13: =SUM(F13,G13) -> 0
F14: =IF(OR(D14="",E14=""),"",D14*E14) | H14: =SUM(F14,G14) -> 0
F15: =IF(OR(D15="",E15=""),"",D15*E15) | H15: =SUM(F15,G15) -> 0
F16: =IF(OR(D16="",E16=""),"",D16*E16) | H16: =SUM(F16,G16) -> 0
... F64: =IF(OR(D64="",E64=""),"",D64*E64) | H64: =SUM(F64,G64) -> 0

Sheet Summary
A1: Summary
A2: Updates automatically from the Income Log and Expense & Mileage Log tabs
A4: Income
A5: Total Received (£) | B5: =SUMIF('Income Log'!F5:F64,"Received",'Income Log'!E5:E64) -> 0
A6: Total Outstanding (£) | B6: =SUMIF('Income Log'!F5:F64,"Outstanding",'Income Log'!E5:E64) -> 0
A7: Payments Logged | B7: =COUNTA('Income Log'!A5:A64) -> 0
A9: Expenses
A10: Total Mileage Claimed (£) | B10: =SUM('Expense & Mileage Log'!F5:F64) -> 0
A11: Total Other Expenses (£) | B11: =SUM('Expense & Mileage Log'!G5:G64) -> 0
A12: Total Expenses Claimed (£) | B12: =SUM('Expense & Mileage Log'!H5:H64) -> 0
A14: Net
A15: Net Income (Received − Expenses Claimed) (£) | B15: =B5-B12 -> 0
A17: Income by Type
A18: Income Type | B18: Total (£)
A19: Day Rate | B19: =SUMIF('Income Log'!D5:D64,"Day Rate",'Income Log'!E5:E64) -> 0
A20: Hourly | B20: =SUMIF('Income Log'!D5:D64,"Hourly",'Income Log'!E5:E64) -> 0
A21: Retainer | B21: =SUMIF('Income Log'!D5:D64,"Retainer",'Income Log'!E5:E64) -> 0
A22: Percentage Fee | B22: =SUMIF('Income Log'!D5:D64,"Percentage Fee",'Income Log'!E5:E64) -> 0
A23: Other | B23: =SUMIF('Income Log'!D5:D64,"Other",'Income Log'!E5:E64) -> 0
A25: Expenses by Category
A26: Category | B26: Total (£)
A27: Mileage | B27: =SUMIF('Expense & Mileage Log'!C5:C64,"Mileage",'Expense & Mileage Log'!H5:H64) -> 0
A28: Software | B28: =SUMIF('Expense & Mileage Log'!C5:C64,"Software",'Expense & Mileage Log'!H5:H64) -> 0
A29: Stationery | B29: =SUMIF('Expense & Mileage Log'!C5:C64,"Stationery",'Expense & Mileage Log'!H5:H64) -> 0
A30: Training | B30: =SUMIF('Expense & Mileage Log'!C5:C64,"Training",'Expense & Mileage Log'!H5:H64) -> 0
A31: Other | B31: =SUMIF('Expense & Mileage Log'!C5:C64,"Other",'Expense & Mileage Log'!H5:H64) -> 0
